{
    "python.pydev.java.home": "C:\\Program Files\\Java\\jdk-10",
    "terminal.integrated.shell.windows": "C:\\Windows\\system32\\cmd.exe",
    "editor.minimap.enabled": true,
    "editor.wordWrap": "on",
    "python.autoComplete.preloadModules": [
        "statsmodels",
        "sqlalchemy",
        "numpy",
        "pandas",
        "matplotlib",
        "seaborn",
        "scipy",
        "sklearn"
    ],
    "autoDocstring.docstringFormat": "numpy",
    "editor.formatOnPaste": true,
    "workbench.activityBar.visible": true,
    "gitlens.advanced.messages": {
        "suppressShowKeyBindingsNotice": true
    },
    "window.menuBarVisibility": "default",
    "TodoParser": {
        "exclude": [
            "cpp",
            "c"
        ],
        "include": [
            "py"
        ],
        "folderExclude": [
            "node_modules",
            ".vscode"
        ],
        "only": [
            "sub-folder/sub-sub-folder"
        ],
        "showInProblems": false,
        "markers": [
            "NOTE:",
            "REMINDER:"
        ],
        "autoDefaultMarkers": true
    },
    "editor.cursorStyle": "line-thin",
    "workbench.iconTheme": "material-icon-theme",
    "material-icon-theme.folders.color": "#90a4ae",
    "workbench.colorCustomizations": {
        "statusBar.background": "#2a0c3dc2",
        "activityBarBadge.background": "#5b02c0",
        "list.activeSelectionForeground": "#616161",
        "list.inactiveSelectionForeground": "#616161",
        "list.highlightForeground": "#616161",
        "scrollbarSlider.activeBackground": "#61616150",
        "editorSuggestWidget.highlightForeground": "#616161",
        "textLink.foreground": "#616161",
        "progressBar.background": "#C6FF00",
        "pickerGroup.foreground": "#616161",
        "tab.activeBorder": "#C6FF00"
    },
    "workbench.sideBar.location": "left",
    "[python]": {
        "editor.codeActionsOnSave": {
            "source.organizeImports": true
        }
    },
    "extensions.ignoreRecommendations": false,
    "python.formatting.provider": "none",
    "materialTheme.cache.workbench.settings": {},
    "workbench.colorTheme": "One Dark Pro"
}